NaaVRE_catalogue_jupyterlab/__init__.py
NaaVRE_catalogue_jupyterlab/_version.py
naavre_catalogue_jupyterlab-0.1.3.data/data/share/jupyter/labextensions/@naavre/catalogue-jupyterlab/package.json
naavre_catalogue_jupyterlab-0.1.3.data/data/share/jupyter/labextensions/@naavre/catalogue-jupyterlab/schemas/@naavre/catalogue-jupyterlab/package.json.orig
naavre_catalogue_jupyterlab-0.1.3.data/data/share/jupyter/labextensions/@naavre/catalogue-jupyterlab/schemas/@naavre/catalogue-jupyterlab/plugin.json
naavre_catalogue_jupyterlab-0.1.3.data/data/share/jupyter/labextensions/@naavre/catalogue-jupyterlab/static/162.006b0b9c456e36d0eab1.js
naavre_catalogue_jupyterlab-0.1.3.data/data/share/jupyter/labextensions/@naavre/catalogue-jupyterlab/static/215.0203594e21154e9ca69f.js
naavre_catalogue_jupyterlab-0.1.3.data/data/share/jupyter/labextensions/@naavre/catalogue-jupyterlab/static/215.0203594e21154e9ca69f.js.LICENSE.txt
naavre_catalogue_jupyterlab-0.1.3.data/data/share/jupyter/labextensions/@naavre/catalogue-jupyterlab/static/25.51082433a1a8e0c6e5a8.js
naavre_catalogue_jupyterlab-0.1.3.data/data/share/jupyter/labextensions/@naavre/catalogue-jupyterlab/static/25.51082433a1a8e0c6e5a8.js.LICENSE.txt
naavre_catalogue_jupyterlab-0.1.3.data/data/share/jupyter/labextensions/@naavre/catalogue-jupyterlab/static/352.0a593aa64ec1e0c598b0.js
naavre_catalogue_jupyterlab-0.1.3.data/data/share/jupyter/labextensions/@naavre/catalogue-jupyterlab/static/433.8bbcb7c3b57ca2596c14.js
naavre_catalogue_jupyterlab-0.1.3.data/data/share/jupyter/labextensions/@naavre/catalogue-jupyterlab/static/487.acd9612963e1f4d90002.js
naavre_catalogue_jupyterlab-0.1.3.data/data/share/jupyter/labextensions/@naavre/catalogue-jupyterlab/static/490.7e671da952c861be27f3.js
naavre_catalogue_jupyterlab-0.1.3.data/data/share/jupyter/labextensions/@naavre/catalogue-jupyterlab/static/543.5018fadcd0cab2d1b73b.js
naavre_catalogue_jupyterlab-0.1.3.dist-info/METADATA
naavre_catalogue_jupyterlab-0.1.3.dist-info/WHEEL
naavre_catalogue_jupyterlab-0.1.3.dist-info/licenses/LICENSE
naavre_catalogue_jupyterlab-0.1.3.dist-info/RECORD
